plaw/__init__.py
plaw/wrapper.py
plaw-0.1.2.dist-info/LICENSE
plaw-0.1.2.dist-info/WHEEL
plaw-0.1.2.dist-info/METADATA
plaw-0.1.2.dist-info/RECORD
