Metadata-Version: 2.1
Name: plaw
Version: 0.1.2
Summary: A simple wrapper for the Lightspeed API
Home-page: https://github.com/holden-nelson/plaw
Keywords: Lightspeed, API, Wrapper
Author: Holden Nelson
Author-email: holden.nathaniel.nelson@gmail.com
Classifier: License :: OSI Approved :: MIT License
Requires-Dist: requests
Requires-Dist: pytz
